nanosearch/__init__.py
nanosearch/cli.py
nanosearch/engine.py
nanosearch/templates/index.html
nanosearch-0.1.2.dist-info/LICENSE
nanosearch-0.1.2.dist-info/METADATA
nanosearch-0.1.2.dist-info/WHEEL
nanosearch-0.1.2.dist-info/entry_points.txt
nanosearch-0.1.2.dist-info/top_level.txt
nanosearch-0.1.2.dist-info/RECORD
