Metadata-Version: 2.1
Name: nanosearch
Version: 0.1.2
Summary: Build a search engine from a website sitemap.
Home-page: https://github.com/capjamesg/nanosearch
Author: capjamesg
Author-email: readers@jamesg.blog
Classifier: Programming Language :: Python :: 3
Classifier: License :: OSI Approved :: Apache Software License
Classifier: Operating System :: OS Independent
Requires-Python: >=3.7
License-File: LICENSE
Requires-Dist: getsitemap
Requires-Dist: numpy
Requires-Dist: requests
Requires-Dist: beautifulsoup4
Requires-Dist: rank-bm25
Requires-Dist: scikit-learn
Provides-Extra: dev
Requires-Dist: flake8 ; extra == 'dev'
Requires-Dist: black ==22.3.0 ; extra == 'dev'
Requires-Dist: isort ; extra == 'dev'
Requires-Dist: twine ; extra == 'dev'
Requires-Dist: pytest ; extra == 'dev'
Requires-Dist: wheel ; extra == 'dev'
Requires-Dist: mkdocs-material ; extra == 'dev'
Requires-Dist: mkdocs ; extra == 'dev'
